_tofcengine.cp38-win_amd64.pyd
nvTOF/__init__.py
nvTOF-1.0.2.data/data/NvIspDll.dll
nvTOF-1.0.2.data/data/libglog.dll
nvTOF-1.0.2.data/data/tof_app.dll
nvTOF-1.0.2.dist-info/METADATA
nvTOF-1.0.2.dist-info/WHEEL
nvTOF-1.0.2.dist-info/top_level.txt
nvTOF-1.0.2.dist-info/RECORD
